peptide_property_predictor/__init__.py
peptide_property_predictor/predict.py
peptide_property_predictor/preprocessing.py
peptide_property_predictor/train.py
peptide_property_predictor/models/small_rt.h5
peptide_property_predictor-0.0.1.dist-info/METADATA
peptide_property_predictor-0.0.1.dist-info/WHEEL
peptide_property_predictor-0.0.1.dist-info/top_level.txt
peptide_property_predictor-0.0.1.dist-info/RECORD
