Metadata-Version: 2.1
Name: peptide-property-predictor
Version: 0.0.1
Summary: A very simple peptide property predictor.
Author-email: Patrick Garrett <pgarrett@scripps.edu>
Project-URL: repository, https://github.com/pgarrett-scripps/PeptidePropertyPredictor.git
Requires-Python: >=3.8
Requires-Dist: pandas
Requires-Dist: scikit-learn
Requires-Dist: tensorflow
Requires-Dist: filterframes
Requires-Dist: numpy
Requires-Dist: matplotlib
